[
  {
    "id": "178f0f09-7fbb-430a-9a62-7dc7bcc55918",
    "data": [
      {
        "text": "Help me",
        "userDefined": false
      }
    ],
    "isTemplate": false,
    "count": 0,
    "lang": "en",
    "updated": 0
  },
  {
    "id": "47aedc6f-3d99-4393-b58b-06973976c43b",
    "data": [
      {
        "text": "What can you do?",
        "userDefined": false
      }
    ],
    "isTemplate": false,
    "count": 0,
    "lang": "en",
    "updated": 0
  },
  {
    "id": "c240903f-83e4-4236-a47f-5cfe64ada8f6",
    "data": [
      {
        "text": "How does this work?",
        "userDefined": false
      }
    ],
    "isTemplate": false,
    "count": 0,
    "lang": "en",
    "updated": 0
  },
  {
    "id": "c7dcd142-46e9-455a-888c-62c48a319120",
    "data": [
      {
        "text": "Give me an example",
        "userDefined": false
      }
    ],
    "isTemplate": false,
    "count": 0,
    "lang": "en",
    "updated": 0
  },
  {
    "id": "688dacf4-b813-4d76-a089-4f44793ed06c",
    "data": [
      {
        "text": "Guide me",
        "userDefined": false
      }
    ],
    "isTemplate": false,
    "count": 0,
    "lang": "en",
    "updated": 0
  }
]